preon/__init__.py
preon/cancer.py
preon/drug.py
preon/normalization.py
preon/examples/__init__.py
preon/tests/__init__.py
preon/tests/normalization_test.py
preon/tests/utils.py
preon-0.1.2.dist-info/licenses/LICENSE
preon-0.1.2.dist-info/METADATA
preon-0.1.2.dist-info/WHEEL
preon-0.1.2.dist-info/top_level.txt
preon-0.1.2.dist-info/RECORD
