Metadata-Version: 2.4
Name: preon
Version: 0.1.2
Home-page: https://github.com/ermshaua/preon
Author: Arik Ermshaus
Author-email: Arik Ermshaus <ermshaua@informatik.hu-berlin.de>
License: BSD 3-Clause License
Project-URL: repository, https://github.com/ermshaua/preon
Keywords: precision-oncology,data-integration,text-mining,normalization,drug-names,cancer-types
Classifier: Intended Audience :: Science/Research
Classifier: Intended Audience :: Developers
Classifier: License :: OSI Approved :: BSD License
Classifier: Programming Language :: Python
Classifier: Topic :: Software Development
Classifier: Topic :: Scientific/Engineering
Classifier: Operating System :: Microsoft :: Windows
Classifier: Operating System :: POSIX
Classifier: Operating System :: Unix
Classifier: Operating System :: MacOS
Classifier: Programming Language :: Python :: 3.7
Classifier: Programming Language :: Python :: 3.8
Classifier: Programming Language :: Python :: 3.9
Classifier: Programming Language :: Python :: 3.10
Classifier: Programming Language :: Python :: 3.11
Classifier: Programming Language :: Python :: 3.12
Requires-Python: >=3.7,<3.13
License-File: LICENSE
Requires-Dist: daproli>=0.22
Requires-Dist: jellyfish>=0.9.0
Requires-Dist: nltk>=3.9
Requires-Dist: numpy<2.3.0,>=1.21.0
Requires-Dist: pandas<2.4.0,>=2.0.0
Requires-Dist: pronto>=2.5.0
Requires-Dist: tqdm>=4.66.3
Requires-Dist: lxml>=4.6.3
Dynamic: author
Dynamic: home-page
Dynamic: license-file
Dynamic: requires-python
